{"LLQ9vVqpxpanAofNnSgsyg==":"photo-1605407160285-3d972384390c.jpeg","Mgk7+uEG4qFXcMNDV60PnA==":"screenshot%202024-11-19%20080439-1083x546.png","8V+fMed9zLv1r1wu8s2pjA==":"screenshot%202024-11-19%20080439-1083x546.png","o8XUMmvKalfRXFuBT9xr4g==":"screenshot%202024-11-19%20081405-1362x591.png","/YRn/8tO6PU8aF/4eBJ+cQ==":"screenshot%202024-11-19%20082532-1084x535.png","DI0pazbzeIof0LwdFPcqzg==":"screenshot%202024-11-19%20082631-1000x502.png","b7AVwurzEjOqNfOZ/M/t8Q==":"photo-1548171916-1d313ff0d812.jpeg","r9rI2Zl2iP2eNIm7ETp01g==":"screenshot%202024-11-19%20083043-1080x543.png","9/4fPZM2UV2lL/ldsBo8iQ==":"screenshot%202024-11-19%20083144-1081x541.png","u7JCipk8fvWe3vVt73utfQ==":"screenshot%202024-11-19%20083246-1080x541.png","SX7QOzRhdCdR5u/iF6owCg==":"screenshot%202024-11-19%20083352-1080x543.png","h/UAOc5v7iR72hib+u3kjw==":"screenshot%202024-11-19%20083434-1080x539.png","C8BWWMMluFNk8UyrBjTAEA==":"photo-1607776905497-b4f788205f6a-1.jpeg","XqStexa3ucYeWEdbgE9USg==":"background1.jpg","kZ2wblpPJ7XChrMqM+YsoQ==":"photo-1634595947394-87012e7b12ba-1.jpeg","nUmWU8BHT3a1TKxwb9fKFw==":"photo-1636289026470-cb40ece1ebc3-1.jpeg","PqianPw/xgmCCZ1jIC2gtA==":"photo-1607776933951-a39fef9e8c35-1.jpeg","JMEcE6iFSmLg+DRwIbJYWw==":"photo-1510682182098-f7c81b805f40-1.jpeg","8WTGv9ZGPnJdkLOZ1YMlIA==":"photo-1533237742545-cdc658d90afb-1.jpeg","KT7Bfr4swOg0L5wmNgS3Kw==":"photo-1625622176640-e2da57f97cf8-1.jpeg","U5puOUgC6pg8u5GdPV91XA==":"67586745074f67b165140f0e1cf9b141-134x129.jpg","9HIW/gakfp7MRKaEVGG6ig==":"f09ea257b351420a1f809f77f20c5999-99x99.jpg","end2Oz2U5c8WUqYCuBzMuw==":"f09ea257b351420a1f809f77f20c5999-removebg-preview-96x96.png","IM65L7pqdAww7xydtnJZZA==":"screenshot%202024-11-19%20083352-1081x544.png","5kVDmM7oXXuRB5ScR6kysA==":"743d1be97557f68c573a024eab738a86-474x711.jpg","AB1d7dTBkDkqcHeZhTsHdg==":"1d267ef35c20b660bb035a9268a69ae5-474x474.jpg","bqVjn8a0ZlB20hKJSwIq/w==":"e2f1d3de3ca5c2f83605e839d8606bc4-474x877.jpg","wwrv8sQBn7EsNcs5YWeKsg==":"e2f1d3de3ca5c2f83605e839d8606bc9-473x378.jpg","NHlH5HRl1tJH0Bg4/vjBSQ==":"c6ed95f42d77d54a0e7d60f919c5d616-712x712.jpg","M6mSmDcP0m3qyBSG65tc7A==":"0c9e02cc9091e27f5dc36b755f1b64c3-474x632.jpg","Sucd9QeutPre+jJXd5+tMA==":"b65b641078d33bb5c7c9b5f20b18ad73-474x474.jpg","fdKfOK/21l/vtiMJxDq6tw==":"721287fb0202f5733851850e1422ee44-473x605.jpg","2j55NArIm7q7i4B/17BOlQ==":"1a37fe47921c22970ec74121b0661f8d-474x792.jpg","OcIuI33Ziny2NuEltBmijg==":"a0550f647598caf424bbf398f48dbaa1-474x711.jpg","fdVH6GjQfI2oOC3PSr7jrw==":"1e26e849516bc3e60f3c7eeeb5b1306e-474x744.jpg","w8prewQvt5qwE6fuzMnLZQ==":"ae5ecb4d4a2b6544ff8bbcda2eef3fdc-473x606.jpg","mcfQJtKl3nI+DIW5hs0Ajw==":"43c2ae74344414eaeb24681527a6b9cf-474x474.jpg","I/+2q2x/7iCvMIpmSAsLGg==":"depositphotos_162374320-stock-illustration-watch-store-logo-removebg-preview-96x102.png","GlPeC9ry5x2eSETni3lEUg==":"depositphotos_162374320-stock-illustration-watch-store-logo-90x96.jpg","QA5sPtwyG3zWJB79wPs/9w==":"depositphotos_162374320-stock-illustration-watch-store-logo-removebg-preview-90x96.png","GZmy3Yg5MpIbEOk16rY6+Q==":"gambar%20whatsapp%202024-12-06%20pukul%2016.32.49_b0485f43-1489x1985.jpg","lPbFrJjjl3nnLLDzpJyMdw==":"hublot%20%E2%80%94%20big%20bang%20meca-10-736x1308.jpg","wD2cgCh/YLqE0LftBckp8A==":"hublot%20%E2%80%94%20big%20bang%20meca-10%20(1)-735x575.jpg","ltlbTjWtxn/wrDbJgSF4Dw==":"black%20minimal%20watch%20advertising%20promotion%20instagram%20post%20-%20templates%20by%20canva-712x712.jpg","+wXs60SQz6PxtXRk6u64WA==":"titan%20watches%20upto%2040%25%20off%20ad%20-%20advert%20gallery-712x887.jpg","mdl3P4Pzy1o6GDrjk/eaNg==":"download%20(11)-712x890.jpg","07+uUSDbUbq0HeOJOeuirg==":"servicing%20your%20watch%20&%20jewelry%20-%20piaget-600x750.jpg","bmc42KwBf13o5hVdB8yMMg==":"raymond%20weil%20caliber%20rw1212%20watch%20movement-600x600.jpg","ejwAsM3YCkY4dXznx+5JUg==":"ronda%20caliber%20756%20watch%20movement-600x600.jpg"}